{"authority":200,"control":"released","controlAcquireTrigger":0,"edges":[],"editable":false,"fitViewOnResize":false,"key":"0e2d33aa-7b56-4728-878e-98499907a52a","legend":{"position":{"units":{"x":"px","y":"px"},"x":50,"y":50},"visible":false},"mode":"pan","nodes":[{"key":"UtIe2vzi5Th","id":"UtIe2vzi5Th","type":"custom","zIndex":4,"measured":{"height":60,"width":72},"position":{"x":891.4782812201747,"y":487.71804867255867},"selected":false,"data":{}},{"key":"v6oBRzFONl5","id":"v6oBRzFONl5","type":"custom","zIndex":4,"measured":{"height":60,"width":72},"position":{"x":1013.7193823467672,"y":487.5647303160037},"selected":false,"data":{}},{"key":"RyBEzHkS7q9","id":"RyBEzHkS7q9","type":"custom","zIndex":4,"measured":{"height":60,"width":72},"position":{"x":767.6821651168041,"y":486.1877083146933},"selected":false,"data":{}},{"key":"kp6pQJdDEmH","id":"kp6pQJdDEmH","type":"custom","zIndex":4,"measured":{"height":60,"width":72},"position":{"x":640.4766181310089,"y":336.781541581349},"selected":false,"data":{}},{"key":"V4xKN19PN8p","id":"V4xKN19PN8p","type":"custom","zIndex":4,"measured":{"height":60,"width":72},"position":{"x":764.9313335722213,"y":336.7087288577552},"selected":false,"data":{}},{"key":"xXYJd3DUmQR","id":"xXYJd3DUmQR","type":"custom","zIndex":4,"measured":{"height":60,"width":72},"position":{"x":888.7323148845874,"y":341.29933932816454},"selected":false,"data":{}},{"key":"p2YkFJIVuat","id":"p2YkFJIVuat","type":"custom","zIndex":4,"measured":{"height":60,"width":72},"position":{"x":651.0883111737313,"y":486.5283239542068},"selected":false,"data":{}},{"key":"i1StPrP7t8X","id":"i1StPrP7t8X","type":"custom","zIndex":4,"measured":{"height":41,"width":40},"position":{"x":884,"y":-136.49999999999997},"selected":false,"data":{}},{"key":"EltSkiu07n0","id":"EltSkiu07n0","type":"custom","zIndex":4,"measured":{"height":105,"width":104},"position":{"x":1143.8333333333333,"y":-142},"selected":false,"data":{}},{"key":"CGyQUQoGeI4","id":"CGyQUQoGeI4","type":"custom","zIndex":4,"measured":{"height":105,"width":104},"position":{"x":1140.833333333333,"y":160.00000000000003},"selected":false,"data":{}},{"key":"yujFCP6rMFg","id":"yujFCP6rMFg","type":"custom","zIndex":4,"measured":{"height":29,"width":32},"position":{"x":668.5,"y":-99.5},"selected":false,"data":{}},{"key":"B4bA9h87HtY","id":"B4bA9h87HtY","type":"custom","zIndex":4,"measured":{"height":29,"width":32},"position":{"x":794.8742218183125,"y":-97.33333333333331},"selected":false,"data":{}},{"key":"MhxluTfxZTp","id":"MhxluTfxZTp","type":"custom","zIndex":4,"measured":{"height":29,"width":32},"position":{"x":787.4449850232218,"y":27.7993595760341},"selected":false,"data":{}},{"key":"ouWyZNj7OtE","id":"ouWyZNj7OtE","type":"custom","zIndex":4,"measured":{"height":26,"width":130},"position":{"x":1131.219096724397,"y":337.8145276784382},"selected":false,"data":{}},{"key":"Y9TBY10CTmj","id":"Y9TBY10CTmj","type":"custom","zIndex":4,"measured":{"height":26,"width":127},"position":{"x":1133.3698938934438,"y":414.24753421344025},"selected":false,"data":{}},{"key":"yE8Tbra1jL8","id":"yE8Tbra1jL8","type":"custom","zIndex":4,"measured":{"height":29,"width":32},"position":{"x":668.1666666666667,"y":27.333333333333336},"selected":false,"data":{}},{"key":"l3AmNBWLRTs","id":"l3AmNBWLRTs","type":"custom","zIndex":4,"measured":{"height":2,"width":2},"position":{"x":881.3255208333333,"y":-9.208333333333336},"selected":false,"data":{}},{"key":"hr8gepuN8JO","id":"hr8gepuN8JO","type":"custom","zIndex":4,"measured":{"height":2,"width":2},"position":{"x":879.9921875,"y":50.79166666666666},"selected":false,"data":{}},{"key":"PfGKCFPyhCe","id":"PfGKCFPyhCe","type":"custom","zIndex":4,"measured":{"height":2,"width":2},"position":{"x":880.1588541666667,"y":-70.70833333333334},"selected":false,"data":{}},{"key":"Cy2njtLIvK2","id":"Cy2njtLIvK2","type":"custom","zIndex":4,"measured":{"height":29,"width":32},"position":{"x":1042.7407764862426,"y":149.43869370153004},"selected":false,"data":{}},{"key":"Gxj6oyi0qrr","id":"Gxj6oyi0qrr","type":"custom","zIndex":4,"measured":{"height":47,"width":165},"position":{"x":944.1666666666669,"y":-137},"selected":false,"data":{}},{"key":"RzIkDDv3WJm","id":"RzIkDDv3WJm","type":"custom","zIndex":4,"measured":{"height":2,"width":2},"position":{"x":946.9921875,"y":-74.16666666666667},"selected":false,"data":{}},{"key":"C7fDxjdoNOo","id":"C7fDxjdoNOo","type":"custom","zIndex":4,"measured":{"height":2,"width":2},"position":{"x":943.1588541666669,"y":48.66666666666666},"selected":false,"data":{}},{"key":"i50V05tzTal","id":"i50V05tzTal","type":"custom","zIndex":4,"measured":{"height":2,"width":2},"position":{"x":938.4921875,"y":-11.666666666666666},"selected":false,"data":{}},{"key":"N9NQhkCS3PK","id":"N9NQhkCS3PK","type":"custom","zIndex":2,"measured":{"height":152,"width":127},"position":{"x":614.8040334109936,"y":441.8269088458048},"selected":false,"data":{}},{"key":"riVqNRurUvl","id":"riVqNRurUvl","type":"custom","zIndex":2,"measured":{"height":2,"width":2},"position":{"x":1053.6071117237366,"y":443.565134199564},"selected":false,"data":{}},{"key":"FVC3vUwh5iu","id":"FVC3vUwh5iu","type":"custom","zIndex":2,"measured":{"height":2,"width":2},"position":{"x":930.2737783904034,"y":443.5651341995641},"selected":false,"data":{}},{"key":"XB94srlpTu8","id":"XB94srlpTu8","type":"custom","zIndex":2,"measured":{"height":2,"width":2},"position":{"x":808.6071117237367,"y":443.04430086623074},"selected":false,"data":{}},{"key":"UHGbnd6Op7R","id":"UHGbnd6Op7R","type":"custom","zIndex":2,"measured":{"height":2,"width":2},"position":{"x":993.6071117237368,"y":292.2109675328975},"selected":false,"data":{}},{"key":"NorOxlctgzg","id":"NorOxlctgzg","type":"custom","zIndex":2,"measured":{"height":2,"width":2},"position":{"x":746.9404450570701,"y":292.2109675328974},"selected":false,"data":{}},{"key":"TtDGUv9Ri5U","id":"TtDGUv9Ri5U","type":"custom","zIndex":2,"measured":{"height":2,"width":2},"position":{"x":870.2737783904035,"y":292.2109675328974},"selected":false,"data":{}},{"key":"ImcKbhA0ZFk","id":"ImcKbhA0ZFk","type":"custom","zIndex":2,"measured":{"height":2,"width":2},"position":{"x":620.2737783904033,"y":-143.62236580043592},"selected":false,"data":{}},{"key":"aOM5M19yIoi","id":"aOM5M19yIoi","type":"custom","zIndex":2,"measured":{"height":2,"width":2},"position":{"x":743.6071117237367,"y":-20.289032467102587},"selected":false,"data":{}},{"key":"S5f1EMGxMiH","id":"S5f1EMGxMiH","type":"custom","zIndex":2,"measured":{"height":2,"width":2},"position":{"x":620.2737783904033,"y":-21.12236580043592},"selected":false,"data":{}},{"key":"rGH63INvjA8","id":"rGH63INvjA8","type":"custom","zIndex":2,"measured":{"height":2,"width":2},"position":{"x":743.6071117237367,"y":-143.62236580043594},"selected":false,"data":{}},{"key":"ENwMyKIGJt9","id":"ENwMyKIGJt9","type":"custom","zIndex":2,"measured":{"height":2,"width":2},"position":{"x":867.7737783904035,"y":-142.7890324671026},"selected":false,"data":{}},{"key":"qMsW7fVLlwV","id":"qMsW7fVLlwV","type":"custom","zIndex":2,"measured":{"height":2,"width":2},"position":{"x":867.7737783904033,"y":40.54430086623076},"selected":false,"data":{}},{"key":"A9YQoMPt3lP","id":"A9YQoMPt3lP","type":"custom","zIndex":2,"measured":{"height":2,"width":2},"position":{"x":866.9404450570701,"y":-21.95569913376923},"selected":false,"data":{}},{"key":"c3vanbF95Ts","id":"c3vanbF95Ts","type":"custom","zIndex":2,"measured":{"height":2,"width":2},"position":{"x":867.7737783904033,"y":-81.95569913376926},"selected":false,"data":{}},{"key":"GOjJS21sjMh","id":"GOjJS21sjMh","type":"custom","zIndex":2,"measured":{"height":2,"width":2},"position":{"x":866.94044505707,"y":-141.95569913376917},"selected":false,"data":{}},{"key":"tRYRcnA9dhm","id":"tRYRcnA9dhm","type":"custom","zIndex":2,"measured":{"height":2,"width":2},"position":{"x":1115.2737783904035,"y":-169.45569913376926},"selected":false,"data":{}},{"key":"UBllMXkxMjg","id":"UBllMXkxMjg","type":"custom","zIndex":2,"measured":{"height":2,"width":2},"position":{"x":1115.2737783904035,"y":-19.45569913376921},"selected":false,"data":{}},{"key":"yxo99krSFxr","id":"yxo99krSFxr","type":"custom","zIndex":2,"measured":{"height":2,"width":2},"position":{"x":1116.1071117237368,"y":129.71096753289743},"selected":false,"data":{}},{"key":"qIzZwJadPfi","id":"qIzZwJadPfi","type":"custom","zIndex":2,"measured":{"height":202,"width":152},"position":{"x":1120.3014734381252,"y":288.8491692476289},"selected":false,"data":{}},{"key":"pXyxriQwe6J","id":"pXyxriQwe6J","type":"custom","zIndex":2,"measured":{"height":2,"width":2},"position":{"x":817.7737783904034,"y":187.21096753289748},"selected":false,"data":{}},{"key":"yqYL0VDwuWe","id":"yqYL0VDwuWe","type":"custom","zIndex":2,"measured":{"height":2,"width":2},"position":{"x":817.7737783904034,"y":114.71096753289748},"selected":false,"data":{}},{"key":"cBOG8cmS9AE","id":"cBOG8cmS9AE","type":"custom","zIndex":4,"measured":{"height":41,"width":40},"position":{"x":885.1666666666665,"y":47.855483766448685},"selected":false,"data":{}},{"key":"dLf57XHtarT","id":"dLf57XHtarT","type":"custom","zIndex":4,"measured":{"height":41,"width":40},"position":{"x":884.1666666666665,"y":-73.14451623355131},"selected":false,"data":{}},{"key":"zz1YKrolF6v","id":"zz1YKrolF6v","type":"custom","zIndex":4,"measured":{"height":41,"width":40},"position":{"x":883.1666666666665,"y":-12.144516233551316},"selected":false,"data":{}},{"key":"sYXbvwRtkKV","id":"sYXbvwRtkKV","type":"custom","zIndex":4,"measured":{"height":47,"width":153},"position":{"x":945.1666666666664,"y":-77.14451623355131},"selected":false,"data":{}},{"key":"k8iTJxBeh5S","id":"k8iTJxBeh5S","type":"custom","zIndex":4,"measured":{"height":47,"width":170},"position":{"x":938.1666666666664,"y":-17.144516233551315},"selected":false,"data":{}},{"key":"qFxdJPzUv1Z","id":"qFxdJPzUv1Z","type":"custom","zIndex":4,"measured":{"height":47,"width":158},"position":{"x":944.1666666666664,"y":42.855483766448685},"selected":false,"data":{}},{"key":"G9lE3CvmmPh","id":"G9lE3CvmmPh","type":"custom","zIndex":2,"measured":{"height":152,"width":127},"position":{"x":739.1595021609933,"y":442.1407259455869},"selected":false,"data":{}},{"key":"ny3NnIxOMSu","id":"ny3NnIxOMSu","type":"custom","zIndex":2,"measured":{"height":152,"width":127},"position":{"x":864.1595021609932,"y":442.5157259455869},"selected":false,"data":{}},{"key":"zYOnWxyynSd","id":"zYOnWxyynSd","type":"custom","zIndex":2,"measured":{"height":152,"width":127},"position":{"x":988.159502160993,"y":442.0157259455869},"selected":false,"data":{}},{"key":"Eyy2OiLiq6X","id":"Eyy2OiLiq6X","type":"custom","zIndex":2,"measured":{"height":152,"width":127},"position":{"x":615.1595021609933,"y":289.01572594558684},"selected":false,"data":{}},{"key":"vawv6tJ3Em2","id":"vawv6tJ3Em2","type":"custom","zIndex":2,"measured":{"height":152,"width":127},"position":{"x":740.1595021609933,"y":289.0157259455869},"selected":false,"data":{}},{"key":"DjAEpX2Ddgd","id":"DjAEpX2Ddgd","type":"custom","zIndex":2,"measured":{"height":152,"width":127},"position":{"x":865.1595021609932,"y":289.0157259455869},"selected":false,"data":{}},{"key":"dFWlWsSxxhO","id":"dFWlWsSxxhO","type":"custom","zIndex":2,"measured":{"height":127,"width":127},"position":{"x":622.1666666666665,"y":-146.64451623355137},"selected":false,"data":{}},{"key":"wr5ncX87Dsx","id":"wr5ncX87Dsx","type":"custom","zIndex":2,"measured":{"height":127,"width":127},"position":{"x":747.1666666666665,"y":-146.64451623355131},"selected":false,"data":{}},{"key":"z85yKDcru40","id":"z85yKDcru40","type":"custom","zIndex":2,"measured":{"height":127,"width":127},"position":{"x":623.1666666666665,"y":-22.644516233551315},"selected":false,"data":{}},{"key":"UKDf9Nbr1fO","id":"UKDf9Nbr1fO","type":"custom","zIndex":2,"measured":{"height":127,"width":127},"position":{"x":746.1666666666665,"y":-23.644516233551315},"selected":false,"data":{}},{"key":"oO96dKEO9Nc","id":"oO96dKEO9Nc","type":"custom","zIndex":2,"measured":{"height":65,"width":252},"position":{"x":870.1666666666665,"y":-146.64451623355131},"selected":false,"data":{}},{"key":"pzdDofmz4Dh","id":"pzdDofmz4Dh","type":"custom","zIndex":2,"measured":{"height":65,"width":252},"position":{"x":871.1666666666665,"y":-84.64451623355131},"selected":false,"data":{}},{"key":"EicvkWrZGnB","id":"EicvkWrZGnB","type":"custom","zIndex":2,"measured":{"height":65,"width":252},"position":{"x":870.1666666666665,"y":-22.644516233551315},"selected":false,"data":{}},{"key":"W5jLanN0C1K","id":"W5jLanN0C1K","type":"custom","zIndex":2,"measured":{"height":65,"width":252},"position":{"x":870.1666666666665,"y":38.355483766448685},"selected":false,"data":{}},{"key":"c9HpomLdf3O","id":"c9HpomLdf3O","type":"custom","zIndex":2,"measured":{"height":312,"width":65},"position":{"x":871.1666666666665,"y":-208.64451623355131},"selected":false,"data":{}},{"key":"SmE3SNRuLog","id":"SmE3SNRuLog","type":"custom","zIndex":2,"measured":{"height":152,"width":152},"position":{"x":1120.1666666666663,"y":-172.64451623355131},"selected":false,"data":{}},{"key":"a97G3U9Qumg","id":"a97G3U9Qumg","type":"custom","zIndex":2,"measured":{"height":152,"width":152},"position":{"x":1118.9401041666663,"y":-24.644516233551315},"selected":false,"data":{}},{"key":"D4450v63d9m","id":"D4450v63d9m","type":"custom","zIndex":4,"measured":{"height":48,"width":110},"position":{"x":654.3202385988076,"y":-206.8847890757872},"selected":false,"data":{}},{"key":"AwSddNnLMVx","id":"AwSddNnLMVx","type":"custom","zIndex":2,"measured":{"height":152,"width":152},"position":{"x":1119.3333333333333,"y":124.60548376644869},"selected":false,"data":{}},{"key":"i1eKeB0jAmd","id":"i1eKeB0jAmd","type":"custom","zIndex":4,"measured":{"height":105,"width":104},"position":{"x":1141.3333333333333,"y":7.605483766448685},"selected":false,"data":{}},{"key":"pl7lH9qH74s","id":"pl7lH9qH74s","type":"custom","zIndex":4,"measured":{"height":29,"width":28},"position":{"x":827.9248438625277,"y":474.0744681205608},"selected":false,"data":{}},{"key":"YjGnqtBIPhg","id":"YjGnqtBIPhg","type":"custom","zIndex":4,"measured":{"height":2,"width":2},"position":{"x":604.565769832684,"y":614.1330824331628},"selected":false,"data":{}},{"key":"guAvxEqaYEN","id":"guAvxEqaYEN","type":"custom","zIndex":4,"measured":{"height":29,"width":132},"position":{"x":683.43716590999,"y":231.92528279846007},"selected":false,"data":{}},{"key":"ysXQFPUAtNh","id":"ysXQFPUAtNh","type":"custom","zIndex":4,"measured":{"height":29,"width":32},"position":{"x":667.7566446064296,"y":146.2874771979427},"selected":false,"data":{}},{"key":"offMVmNOxnL","id":"offMVmNOxnL","type":"custom","zIndex":4,"measured":{"height":29,"width":32},"position":{"x":920.2902751393468,"y":159.0390612100432},"selected":false,"data":{}},{"key":"DukDroxN0ec","id":"DukDroxN0ec","type":"custom","zIndex":4,"measured":{"height":60,"width":72},"position":{"x":1012.6059547742586,"y":335.3143105325198},"selected":false,"data":{}},{"key":"lwnjQauY6NM","id":"lwnjQauY6NM","type":"custom","zIndex":2,"measured":{"height":127,"width":127},"position":{"x":747.6823803464191,"y":100.14386162489532},"selected":false,"data":{}},{"key":"VdFl69KRUv1","id":"VdFl69KRUv1","type":"custom","zIndex":2,"measured":{"height":152,"width":127},"position":{"x":989.8237980526528,"y":289.0695227809323},"selected":false,"data":{}},{"key":"tDsXbBZfvKg","id":"tDsXbBZfvKg","type":"custom","zIndex":2,"measured":{"height":127,"width":127},"position":{"x":625.5733591821343,"y":100.1438616248952},"selected":false,"data":{}},{"key":"Lvfj218ymdb","id":"Lvfj218ymdb","type":"custom","zIndex":4,"measured":{"height":29,"width":28},"position":{"x":709.4463100436458,"y":467.7561157916105},"selected":false,"data":{}},{"key":"c3Vabb5Ty7c","id":"c3Vabb5Ty7c","type":"custom","zIndex":2,"measured":{"height":65,"width":252},"position":{"x":870.4336216354045,"y":-208.25571690019427},"selected":false,"data":{}},{"key":"gUDJiIx80cv","id":"gUDJiIx80cv","type":"custom","zIndex":4,"measured":{"height":41,"width":40},"position":{"x":884.4336216354046,"y":-194.25571690019427},"selected":false,"data":{}},{"key":"cIkrt2V5fpI","id":"cIkrt2V5fpI","type":"custom","zIndex":4,"measured":{"height":47,"width":134},"position":{"x":956.4336216354044,"y":-198.25571690019427},"selected":false,"data":{}},{"key":"REqs30FA8Of","id":"REqs30FA8Of","type":"custom","zIndex":4,"measured":{"height":29,"width":32},"position":{"x":793.7305828883234,"y":160.81375516027944},"selected":false,"data":{}},{"key":"VH4cbjmL4hD","id":"VH4cbjmL4hD","type":"custom","zIndex":4,"measured":{"height":29,"width":136},"position":{"x":920.087401937997,"y":233.18175152509264},"selected":false,"data":{}},{"key":"tMrMu0Pmjfn","id":"tMrMu0Pmjfn","type":"custom","zIndex":2,"measured":{"height":127,"width":127},"position":{"x":871.8420710281216,"y":99.93274234543662},"selected":false,"data":{}},{"key":"O66ZPlJa0DA","id":"O66ZPlJa0DA","type":"custom","zIndex":2,"measured":{"height":127,"width":127},"position":{"x":995.9014933678014,"y":99.93274234543662},"selected":false,"data":{}},{"key":"OeEuC0uKsoj","id":"OeEuC0uKsoj","type":"custom","zIndex":2,"measured":{"height":66,"width":252},"position":{"x":870.6933726731247,"y":223.9921646851164},"selected":false,"data":{}},{"key":"F6ZltYvReJn","id":"F6ZltYvReJn","type":"custom","zIndex":2,"measured":{"height":66,"width":247},"position":{"x":626.0206230587561,"y":223.9921646851164},"selected":false,"data":{}}],"props":{"AVTOkFb0WrE":{"backgroundColor":[8,8,8,0],"borderRadius":3,"color":[43,32,243,1],"dimensions":{"height":150,"width":125},"key":"box","label":{"align":"center","direction":"x","label":"","level":"p","maxInlineSize":150,"orientation":"top"},"orientation":"left","scale":1,"strokeWidth":2},"AwSddNnLMVx":{"backgroundColor":[8,8,8,0],"borderRadius":3,"color":[243,32,36,1],"dimensions":{"height":150,"width":150},"key":"box","label":{"align":"center","direction":"x","label":"","level":"p","maxInlineSize":150,"orientation":"top"},"orientation":"left","scale":1,"strokeWidth":2},"B4bA9h87HtY":{"control":{"chip":{"sink":{"props":{"authority":255,"channel":1048769},"type":"acquire-channel-control","valueType":"boolean","variant":"sink"},"source":{"props":{"channel":1048769},"type":"controlled-status-source","valueType":"status","variant":"source"}},"indicator":{"statusSource":{"props":{"channel":1048769},"type":"controlled-status-source","valueType":"status","variant":"source"}},"orientation":"bottom","show":true,"showChip":true,"showIndicator":true},"key":"switch","label":{"align":"center","direction":"x","label":"Arm Abort","level":"p","maxInlineSize":150,"orientation":"top"},"orientation":"left","scale":null,"sink":{"props":{"connections":[{"from":"setpoint","to":"setter"}],"inlet":"setpoint","segments":{"setpoint":{"props":{"falsy":0,"truthy":1},"type":"boolean-numeric-converter-sink","valueType":"boolean","variant":"sink"},"setter":{"props":{"channel":1048769},"type":"controlled-numeric-telem-sink","valueType":"number","variant":"sink"}}},"type":"sink-pipeline","valueType":"boolean","variant":"sink"},"source":{"props":{"connections":[{"from":"valueStream","to":"threshold"}],"outlet":"threshold","segments":{"threshold":{"props":{"trueBound":{"lower":0.9,"upper":1.1}},"type":"boolean-source","valueType":"boolean","variant":"source"},"valueStream":{"props":{"channel":1048774},"type":"stream-channel-value","valueType":"number","variant":"source"}}},"type":"source-pipeline","valueType":"boolean","variant":"source"}},"CGyQUQoGeI4":{"color":[243,32,36,1],"key":"light","label":{"align":"center","direction":"x","label":"Abort Active","level":"p","maxInlineSize":150,"orientation":"top"},"orientation":"left","scale":2,"source":{"props":{"connections":[{"from":"valueStream","to":"threshold"}],"outlet":"threshold","segments":{"threshold":{"props":{"trueBound":{"lower":0.9,"upper":1.1}},"type":"boolean-source","valueType":"boolean","variant":"source"},"valueStream":{"props":{"channel":1048771},"type":"stream-channel-value","valueType":"number","variant":"source"}}},"type":"source-pipeline","valueType":"boolean","variant":"source"}},"Cy2njtLIvK2":{"control":{"chip":{"sink":{"props":{"authority":255,"channel":1048785},"type":"acquire-channel-control","valueType":"boolean","variant":"sink"},"source":{"props":{"channel":1048785},"type":"controlled-status-source","valueType":"status","variant":"source"}},"indicator":{"statusSource":{"props":{"channel":1048785},"type":"controlled-status-source","valueType":"status","variant":"source"}},"show":true,"showChip":true,"showIndicator":true},"key":"switch","label":{"align":"center","direction":"x","label":"Record Data","level":"p","maxInlineSize":150,"orientation":"top"},"orientation":"left","scale":null,"sink":{"props":{"connections":[{"from":"setpoint","to":"setter"}],"inlet":"setpoint","segments":{"setpoint":{"props":{"falsy":0,"truthy":1},"type":"boolean-numeric-converter-sink","valueType":"boolean","variant":"sink"},"setter":{"props":{"channel":1048785},"type":"controlled-numeric-telem-sink","valueType":"number","variant":"sink"}}},"type":"sink-pipeline","valueType":"boolean","variant":"sink"},"source":{"props":{"connections":[{"from":"valueStream","to":"threshold"}],"outlet":"threshold","segments":{"threshold":{"props":{"trueBound":{"lower":0.9,"upper":1.1}},"type":"boolean-source","valueType":"boolean","variant":"source"},"valueStream":{"props":{"channel":1048785},"type":"stream-channel-value","valueType":"number","variant":"source"}}},"type":"source-pipeline","valueType":"boolean","variant":"source"}},"D4450v63d9m":{"":{"tooltip":["T_CLOCK_S"]},"color":[250,250,250,1],"inlineSize":70,"key":"value","label":{"align":"center","direction":"x","label":"Time(S)","level":"p","maxInlineSize":150,"orientation":"top"},"level":"h2","orientation":"left","redline":{"bounds":{"lower":0,"upper":1},"gradient":[]},"scale":1,"stalenessColor":[0,0,0,0],"stalenessTimeout":5,"telem":{"props":{"connections":[{"from":"valueStream","to":"rollingAverage"},{"from":"rollingAverage","to":"stringifier"}],"outlet":"stringifier","segments":{"rollingAverage":{"props":{"windowSize":1},"type":"rolling-average","valueType":"number","variant":"source"},"stringifier":{"props":{"notation":"standard","precision":2},"type":"stringify-number","valueType":"string","variant":"source"},"valueStream":{"props":{"channel":1048760},"type":"stream-channel-value","valueType":"number","variant":"source"}}},"type":"source-pipeline","valueType":"string","variant":"source"},"tooltip":["T_CLOCK_MS"],"units":"s"},"DjAEpX2Ddgd":{"backgroundColor":[8,8,8,0],"borderRadius":3,"color":[193,32,243,1],"dimensions":{"height":150,"width":125},"key":"box","label":{"align":"center","direction":"x","label":"","level":"p","maxInlineSize":150,"orientation":"top"},"orientation":"left","scale":1,"strokeWidth":2},"DukDroxN0ec":{"color":[250,250,250,1],"control":{"chip":{"sink":{"props":{"authority":255,"channel":1048697},"type":"acquire-channel-control","valueType":"boolean","variant":"sink"},"source":{"props":{"channel":1048697},"type":"controlled-status-source","valueType":"status","variant":"source"}},"indicator":{"statusSource":{"props":{"channel":1048697},"type":"controlled-status-source","valueType":"status","variant":"source"}},"show":true,"showChip":true,"showIndicator":true},"key":"solenoidValve","label":{"align":"center","direction":"x","label":"Cameras","level":"p","maxInlineSize":150,"orientation":"top"},"normallyOpen":true,"orientation":"left","scale":1,"sink":{"props":{"connections":[{"from":"setpoint","to":"setter"}],"inlet":"setpoint","segments":{"setpoint":{"props":{"falsy":0,"truthy":1},"type":"boolean-numeric-converter-sink","valueType":"boolean","variant":"sink"},"setter":{"props":{"channel":1048697},"type":"controlled-numeric-telem-sink","valueType":"number","variant":"sink"}}},"type":"sink-pipeline","valueType":"boolean","variant":"sink"},"source":{"props":{"connections":[{"from":"valueStream","to":"threshold"}],"outlet":"threshold","segments":{"threshold":{"props":{"trueBound":{"lower":0.9,"upper":1.1}},"type":"boolean-source","valueType":"boolean","variant":"source"},"valueStream":{"props":{"channel":1048698},"type":"stream-channel-value","valueType":"number","variant":"source"}}},"type":"source-pipeline","valueType":"boolean","variant":"source"}},"EicvkWrZGnB":{"backgroundColor":[8,8,8,0],"borderRadius":3,"color":[243,32,36,1],"dimensions":{"height":62.5,"width":250},"key":"box","label":{"align":"center","direction":"x","label":"","level":"p","maxInlineSize":150,"orientation":"top"},"orientation":"left","scale":1,"strokeWidth":2},"EltSkiu07n0":{"color":[52,198,26,1],"key":"light","label":{"align":"center","direction":"x","label":"Sequence Active","level":"p","maxInlineSize":150,"orientation":"top"},"orientation":"left","scale":2,"source":{"props":{"connections":[{"from":"valueStream","to":"threshold"}],"outlet":"threshold","segments":{"threshold":{"props":{"trueBound":{"lower":0.9,"upper":1.1}},"type":"boolean-source","valueType":"boolean","variant":"source"},"valueStream":{"props":{"channel":1048772},"type":"stream-channel-value","valueType":"number","variant":"source"}}},"type":"source-pipeline","valueType":"boolean","variant":"source"}},"Eyy2OiLiq6X":{"backgroundColor":[8,8,8,0],"borderRadius":3,"color":[193,32,243,1],"dimensions":{"height":150,"width":125},"key":"box","label":{"align":"center","direction":"x","label":"","level":"p","maxInlineSize":150,"orientation":"top"},"orientation":"left","scale":1,"strokeWidth":2},"F6ZltYvReJn":{"backgroundColor":[8,8,8,0],"borderRadius":3,"color":[243,32,36,1],"dimensions":{"height":64,"width":245},"key":"box","label":{"align":"center","direction":"x","label":"","level":"p","maxInlineSize":150,"orientation":"top"},"orientation":"left","scale":1,"strokeWidth":2},"G9lE3CvmmPh":{"backgroundColor":[8,8,8,0],"borderRadius":3,"color":[43,32,243,1],"dimensions":{"height":150,"width":125},"key":"box","label":{"align":"center","direction":"x","label":"","level":"p","maxInlineSize":150,"orientation":"top"},"orientation":"left","scale":1,"strokeWidth":2},"GYmsgXGJLLc":{"backgroundColor":[8,8,8,0],"borderRadius":3,"color":[43,32,243,1],"dimensions":{"height":150,"width":125},"key":"box","label":{"align":"center","direction":"x","label":"","level":"p","maxInlineSize":150,"orientation":"top"},"orientation":"left","scale":1,"strokeWidth":2},"Gxj6oyi0qrr":{"align":"center","autoFit":true,"color":[250,250,250,1],"dimensions":{"height":200,"width":125},"key":"textBox","label":{"align":"center","direction":"x","label":"Text Box","level":"p","maxInlineSize":150,"orientation":"top"},"level":"h2","orientation":"left","scale":1,"value":"Abort Status","width":75},"ICxTXq7cCZ6":{"color":[52,198,26,1],"key":"light","label":{"align":"center","direction":"x","label":"","level":"p","maxInlineSize":150,"orientation":"top"},"orientation":"left","scale":0.75,"source":{"props":{"connections":[{"from":"valueStream","to":"threshold"}],"outlet":"threshold","segments":{"threshold":{"props":{"trueBound":{"lower":0.9,"upper":1.1}},"type":"boolean-source","valueType":"boolean","variant":"source"},"valueStream":{"props":{"channel":0},"type":"stream-channel-value","valueType":"number","variant":"source"}}},"type":"source-pipeline","valueType":"boolean","variant":"source"}},"Lvfj218ymdb":{"color":[250,250,250,1],"key":"light","label":{"align":"center","direction":"x","label":"","level":"p","maxInlineSize":150,"orientation":"top"},"orientation":"left","scale":0.5,"source":{"props":{"connections":[{"from":"valueStream","to":"threshold"}],"outlet":"threshold","segments":{"threshold":{"props":{"trueBound":{"lower":0.9,"upper":1.1}},"type":"boolean-source","valueType":"boolean","variant":"source"},"valueStream":{"props":{"channel":1048790},"type":"stream-channel-value","valueType":"number","variant":"source"}}},"type":"source-pipeline","valueType":"boolean","variant":"source"}},"Lz8ZbknE1RS":{"color":[55,116,208,1],"control":{"show":true},"key":"button","label":{"align":"center","direction":"x","label":"Clear Prepress Hold","level":"h4","maxInlineSize":150,"orientation":"top"},"mode":"fire","onClickDelay":0,"orientation":"left","scale":null,"sink":{"props":{"connections":[{"from":"setpoint","to":"setter"}],"inlet":"setpoint","segments":{"setpoint":{"props":{"falsy":0,"truthy":1},"type":"boolean-numeric-converter-sink","valueType":"boolean","variant":"sink"},"setter":{"props":{"channel":0},"type":"controlled-numeric-telem-sink","valueType":"number","variant":"sink"}}},"type":"sink-pipeline","valueType":"boolean","variant":"sink"}},"MhxluTfxZTp":{"control":{"chip":{"sink":{"props":{"authority":255,"channel":1048770},"type":"acquire-channel-control","valueType":"boolean","variant":"sink"},"source":{"props":{"channel":1048770},"type":"controlled-status-source","valueType":"status","variant":"source"}},"indicator":{"statusSource":{"props":{"channel":1048770},"type":"controlled-status-source","valueType":"status","variant":"source"}},"show":true,"showChip":true,"showIndicator":true},"key":"switch","label":{"align":"center","direction":"x","label":"ABORT","level":"p","maxInlineSize":150,"orientation":"top"},"orientation":"left","scale":null,"sink":{"props":{"connections":[{"from":"setpoint","to":"setter"}],"inlet":"setpoint","segments":{"setpoint":{"props":{"falsy":0,"truthy":1},"type":"boolean-numeric-converter-sink","valueType":"boolean","variant":"sink"},"setter":{"props":{"channel":1048770},"type":"controlled-numeric-telem-sink","valueType":"number","variant":"sink"}}},"type":"sink-pipeline","valueType":"boolean","variant":"sink"},"source":{"props":{"connections":[{"from":"valueStream","to":"threshold"}],"outlet":"threshold","segments":{"threshold":{"props":{"trueBound":{"lower":0.9,"upper":1.1}},"type":"boolean-source","valueType":"boolean","variant":"source"},"valueStream":{"props":{"channel":1048770},"type":"stream-channel-value","valueType":"number","variant":"source"}}},"type":"source-pipeline","valueType":"boolean","variant":"source"}},"N9NQhkCS3PK":{"backgroundColor":[8,8,8,0],"borderRadius":3,"color":[43,32,243,1],"dimensions":{"height":150,"width":125},"key":"box","label":{"align":"center","direction":"x","label":"","level":"p","maxInlineSize":150,"orientation":"top"},"orientation":"left","scale":1,"strokeWidth":2},"NV454xdFldZ":{"backgroundColor":[8,8,8,0],"borderRadius":3,"color":[31,169,204,1],"dimensions":{"height":175,"width":250},"key":"box","label":{"align":"center","direction":"x","label":"","level":"p","maxInlineSize":150,"orientation":"top"},"orientation":"left","scale":1,"strokeWidth":2},"O66ZPlJa0DA":{"backgroundColor":[8,8,8,0],"borderRadius":3,"color":[243,32,36,1],"dimensions":{"height":125,"width":125},"key":"box","label":{"align":"center","direction":"x","label":"","level":"p","maxInlineSize":150,"orientation":"top"},"orientation":"left","scale":1,"strokeWidth":2},"OeEuC0uKsoj":{"backgroundColor":[8,8,8,0],"borderRadius":3,"color":[243,32,36,1],"dimensions":{"height":64,"width":250},"key":"box","label":{"align":"center","direction":"x","label":"","level":"p","maxInlineSize":150,"orientation":"top"},"orientation":"left","scale":1,"strokeWidth":2},"REqs30FA8Of":{"control":{"chip":{"sink":{"props":{"authority":255,"channel":1048786},"type":"acquire-channel-control","valueType":"boolean","variant":"sink"},"source":{"props":{"channel":1048786},"type":"controlled-status-source","valueType":"status","variant":"source"}},"indicator":{"statusSource":{"props":{"channel":1048786},"type":"controlled-status-source","valueType":"status","variant":"source"}},"show":true,"showChip":true,"showIndicator":true},"key":"switch","label":{"align":"center","direction":"x","label":"COPV Manual Override","level":"p","maxInlineSize":125,"orientation":"top"},"orientation":"left","scale":null,"sink":{"props":{"connections":[{"from":"setpoint","to":"setter"}],"inlet":"setpoint","segments":{"setpoint":{"props":{"falsy":0,"truthy":1},"type":"boolean-numeric-converter-sink","valueType":"boolean","variant":"sink"},"setter":{"props":{"channel":1048786},"type":"controlled-numeric-telem-sink","valueType":"number","variant":"sink"}}},"type":"sink-pipeline","valueType":"boolean","variant":"sink"},"source":{"props":{"connections":[{"from":"valueStream","to":"threshold"}],"outlet":"threshold","segments":{"threshold":{"props":{"trueBound":{"lower":0.9,"upper":1.1}},"type":"boolean-source","valueType":"boolean","variant":"source"},"valueStream":{"props":{"channel":1048787},"type":"stream-channel-value","valueType":"number","variant":"source"}}},"type":"source-pipeline","valueType":"boolean","variant":"source"}},"RyBEzHkS7q9":{"color":[250,250,250,1],"control":{"chip":{"sink":{"props":{"authority":255,"channel":1048799},"type":"acquire-channel-control","valueType":"boolean","variant":"sink"},"source":{"props":{"channel":1048799},"type":"controlled-status-source","valueType":"status","variant":"source"}},"indicator":{"statusSource":{"props":{"channel":1048799},"type":"controlled-status-source","valueType":"status","variant":"source"}},"show":true,"showChip":true,"showIndicator":true},"key":"solenoidValve","label":{"align":"center","direction":"x","label":"PV-WA-04","level":"p","maxInlineSize":150,"orientation":"top"},"normallyOpen":false,"orientation":"left","scale":1,"sink":{"props":{"connections":[{"from":"setpoint","to":"setter"}],"inlet":"setpoint","segments":{"setpoint":{"props":{"falsy":0,"truthy":1},"type":"boolean-numeric-converter-sink","valueType":"boolean","variant":"sink"},"setter":{"props":{"channel":1048799},"type":"controlled-numeric-telem-sink","valueType":"number","variant":"sink"}}},"type":"sink-pipeline","valueType":"boolean","variant":"sink"},"source":{"props":{"connections":[{"from":"valueStream","to":"threshold"}],"outlet":"threshold","segments":{"threshold":{"props":{"trueBound":{"lower":0.9,"upper":1.1}},"type":"boolean-source","valueType":"boolean","variant":"source"},"valueStream":{"props":{"channel":1048800},"type":"stream-channel-value","valueType":"number","variant":"source"}}},"type":"source-pipeline","valueType":"boolean","variant":"source"}},"SVQuuEwHse2":{"color":[52,198,26,1],"key":"light","label":{"align":"center","direction":"x","label":"","level":"p","maxInlineSize":150,"orientation":"top"},"orientation":"left","scale":0.75,"source":{"props":{"connections":[{"from":"valueStream","to":"threshold"}],"outlet":"threshold","segments":{"threshold":{"props":{"trueBound":{"lower":0.9,"upper":1.1}},"type":"boolean-source","valueType":"boolean","variant":"source"},"valueStream":{"props":{"channel":0},"type":"stream-channel-value","valueType":"number","variant":"source"}}},"type":"source-pipeline","valueType":"boolean","variant":"source"}},"SmE3SNRuLog":{"backgroundColor":[8,8,8,0],"borderRadius":3,"color":[243,32,36,1],"dimensions":{"height":150,"width":150},"key":"box","label":{"align":"center","direction":"x","label":"","level":"p","maxInlineSize":150,"orientation":"top"},"orientation":"left","scale":1,"strokeWidth":2},"UKDf9Nbr1fO":{"backgroundColor":[243,32,36,1],"borderRadius":3,"color":[243,32,36,1],"dimensions":{"height":125,"width":125},"key":"box","label":{"align":"center","direction":"x","label":"","level":"p","maxInlineSize":150,"orientation":"top"},"orientation":"left","scale":1,"strokeWidth":2},"UtIe2vzi5Th":{"color":[250,250,250,1],"control":{"chip":{"sink":{"props":{"authority":255,"channel":1048655},"type":"acquire-channel-control","valueType":"boolean","variant":"sink"},"source":{"props":{"channel":1048655},"type":"controlled-status-source","valueType":"status","variant":"source"}},"indicator":{"statusSource":{"props":{"channel":1048655},"type":"controlled-status-source","valueType":"status","variant":"source"}},"show":true,"showChip":true,"showIndicator":true},"key":"solenoidValve","label":{"align":"center","direction":"x","label":"Igniter","level":"p","maxInlineSize":150,"orientation":"top"},"normallyOpen":true,"orientation":"left","scale":1,"sink":{"props":{"connections":[{"from":"setpoint","to":"setter"}],"inlet":"setpoint","segments":{"setpoint":{"props":{"falsy":0,"truthy":1},"type":"boolean-numeric-converter-sink","valueType":"boolean","variant":"sink"},"setter":{"props":{"channel":1048655},"type":"controlled-numeric-telem-sink","valueType":"number","variant":"sink"}}},"type":"sink-pipeline","valueType":"boolean","variant":"sink"},"source":{"props":{"connections":[{"from":"valueStream","to":"threshold"}],"outlet":"threshold","segments":{"threshold":{"props":{"trueBound":{"lower":0.9,"upper":1.1}},"type":"boolean-source","valueType":"boolean","variant":"source"},"valueStream":{"props":{"channel":1048656},"type":"stream-channel-value","valueType":"number","variant":"source"}}},"type":"source-pipeline","valueType":"boolean","variant":"source"}},"V4xKN19PN8p":{"color":[250,250,250,1],"control":{"chip":{"sink":{"props":{"authority":255,"channel":1048651},"type":"acquire-channel-control","valueType":"boolean","variant":"sink"},"source":{"props":{"channel":1048651},"type":"controlled-status-source","valueType":"status","variant":"source"}},"indicator":{"statusSource":{"props":{"channel":1048651},"type":"controlled-status-source","valueType":"status","variant":"source"}},"show":true,"showChip":true,"showIndicator":true},"key":"solenoidValve","label":{"align":"center","direction":"x","label":"Vent QDs","level":"p","maxInlineSize":150,"orientation":"top"},"normallyOpen":true,"orientation":"left","scale":1,"sink":{"props":{"connections":[{"from":"setpoint","to":"setter"}],"inlet":"setpoint","segments":{"setpoint":{"props":{"falsy":0,"truthy":1},"type":"boolean-numeric-converter-sink","valueType":"boolean","variant":"sink"},"setter":{"props":{"channel":1048651},"type":"controlled-numeric-telem-sink","valueType":"number","variant":"sink"}}},"type":"sink-pipeline","valueType":"boolean","variant":"sink"},"source":{"props":{"connections":[{"from":"valueStream","to":"threshold"}],"outlet":"threshold","segments":{"threshold":{"props":{"trueBound":{"lower":0.9,"upper":1.1}},"type":"boolean-source","valueType":"boolean","variant":"source"},"valueStream":{"props":{"channel":1048652},"type":"stream-channel-value","valueType":"number","variant":"source"}}},"type":"source-pipeline","valueType":"boolean","variant":"source"}},"VH4cbjmL4hD":{"color":[55,116,208,1],"control":{"chip":{"sink":{"props":{"authority":255,"channel":1048768},"type":"acquire-channel-control","valueType":"boolean","variant":"sink"},"source":{"props":{"channel":1048768},"type":"controlled-status-source","valueType":"status","variant":"source"}},"indicator":{"statusSource":{"props":{"channel":1048768},"type":"controlled-status-source","valueType":"status","variant":"source"}},"show":true,"showChip":true,"showIndicator":true},"key":"button","label":{"align":"center","direction":"x","label":"Shutdown Scripts","level":"p","maxInlineSize":150,"orientation":"top"},"mode":"fire","onClickDelay":0,"orientation":"left","scale":null,"sink":{"props":{"connections":[{"from":"setpoint","to":"setter"}],"inlet":"setpoint","segments":{"setpoint":{"props":{"falsy":0,"truthy":1},"type":"boolean-numeric-converter-sink","valueType":"boolean","variant":"sink"},"setter":{"props":{"channel":1048768},"type":"controlled-numeric-telem-sink","valueType":"number","variant":"sink"}}},"type":"sink-pipeline","valueType":"boolean","variant":"sink"}},"VdFl69KRUv1":{"backgroundColor":[8,8,8,0],"borderRadius":3,"color":[43,32,243,1],"dimensions":{"height":150,"width":125},"key":"box","label":{"align":"center","direction":"x","label":"","level":"p","maxInlineSize":150,"orientation":"top"},"orientation":"left","scale":1,"strokeWidth":2},"W5jLanN0C1K":{"backgroundColor":[8,8,8,0],"borderRadius":3,"color":[243,32,36,1],"dimensions":{"height":62.5,"width":250},"key":"box","label":{"align":"center","direction":"x","label":"","level":"p","maxInlineSize":150,"orientation":"top"},"orientation":"left","scale":1,"strokeWidth":2},"WoiW2XkQC3d":{"align":"center","autoFit":true,"color":[250,250,250,1],"dimensions":{"height":200,"width":125},"key":"textBox","label":{"align":"center","direction":"x","label":"Text Box","level":"p","maxInlineSize":150,"orientation":"top"},"level":"h2","orientation":"left","scale":1,"value":"Abort Active","width":75},"Y9TBY10CTmj":{"color":[250,250,250,1],"control":{"chip":{"sink":{"props":{"authority":255,"channel":1048763},"type":"acquire-channel-control","valueType":"boolean","variant":"sink"},"source":{"props":{"channel":1048763},"type":"controlled-status-source","valueType":"status","variant":"source"}},"indicator":{"statusSource":{"props":{"channel":1048763},"type":"controlled-status-source","valueType":"status","variant":"source"}},"showChip":true,"showIndicator":true},"disabled":false,"key":"setpoint","label":{"align":"center","direction":"x","label":"","level":"p","maxInlineSize":150,"orientation":"top"},"orientation":"left","scale":1,"sink":{"props":{"connections":[],"inlet":"setter","segments":{"setter":{"props":{"channel":1048763},"type":"controlled-numeric-telem-sink","valueType":"number","variant":"sink"}}},"type":"sink-pipeline","valueType":"number","variant":"sink"},"size":"small","source":{"props":{"connections":[],"outlet":"valueStream","segments":{"valueStream":{"props":{"channel":0},"type":"stream-channel-value","valueType":"number","variant":"source"}}},"type":"source-pipeline","valueType":"number","variant":"source"},"units":"S"},"ZrlsIrXM3cm":{"color":[250,250,250,1],"key":"light","label":{"align":"center","direction":"x","label":"Light","level":"p","maxInlineSize":150,"orientation":"top"},"orientation":"left","scale":1,"source":{"props":{"connections":[{"from":"valueStream","to":"threshold"}],"outlet":"threshold","segments":{"threshold":{"props":{"trueBound":{"lower":0.9,"upper":1.1}},"type":"boolean-source","valueType":"boolean","variant":"source"},"valueStream":{"props":{"channel":0},"type":"stream-channel-value","valueType":"number","variant":"source"}}},"type":"source-pipeline","valueType":"boolean","variant":"source"}},"a97G3U9Qumg":{"backgroundColor":[8,8,8,0],"borderRadius":3,"color":[243,32,36,1],"dimensions":{"height":150,"width":150},"key":"box","label":{"align":"center","direction":"x","label":"","level":"p","maxInlineSize":150,"orientation":"top"},"orientation":"left","scale":1,"strokeWidth":2},"aLMjvHLhm9r":{"backgroundColor":[8,8,8,0],"borderRadius":3,"color":[43,32,243,1],"dimensions":{"height":150,"width":125},"key":"box","label":{"align":"center","direction":"x","label":"","level":"p","maxInlineSize":150,"orientation":"top"},"orientation":"left","scale":1,"strokeWidth":2},"c3Vabb5Ty7c":{"backgroundColor":[8,8,8,0],"borderRadius":3,"color":[243,32,36,1],"dimensions":{"height":62.5,"width":250},"key":"box","label":{"align":"center","direction":"x","label":"","level":"p","maxInlineSize":150,"orientation":"top"},"orientation":"left","scale":1,"strokeWidth":2},"c9HpomLdf3O":{"backgroundColor":[8,8,8,0],"borderRadius":3,"color":[243,32,36,1],"dimensions":{"height":310,"width":62.5},"key":"box","label":{"align":"center","direction":"x","label":"","level":"p","maxInlineSize":150,"orientation":"top"},"orientation":"left","scale":1,"strokeWidth":2},"cBOG8cmS9AE":{"color":[52,198,26,1],"key":"light","label":{"align":"center","direction":"x","label":"","level":"p","maxInlineSize":150,"orientation":"top"},"orientation":"left","scale":0.75,"source":{"props":{"connections":[{"from":"valueStream","to":"threshold"}],"outlet":"threshold","segments":{"threshold":{"props":{"trueBound":{"lower":0.9,"upper":1.1}},"type":"boolean-source","valueType":"boolean","variant":"source"},"valueStream":{"props":{"channel":1048778},"type":"stream-channel-value","valueType":"number","variant":"source"}}},"type":"source-pipeline","valueType":"boolean","variant":"source"}},"cIkrt2V5fpI":{"align":"center","autoFit":true,"color":[250,250,250,1],"dimensions":{"height":200,"width":125},"key":"textBox","label":{"align":"center","direction":"x","label":"Text Box","level":"p","maxInlineSize":150,"orientation":"top"},"level":"h2","orientation":"left","scale":1,"value":"COPV Full","width":75},"dFWlWsSxxhO":{"backgroundColor":[8,8,8,0],"borderRadius":3,"color":[243,32,36,1],"dimensions":{"height":125,"width":125},"key":"box","label":{"align":"center","direction":"x","label":"","level":"p","maxInlineSize":150,"orientation":"top"},"orientation":"left","scale":1,"strokeWidth":2},"dLf57XHtarT":{"color":[52,198,26,1],"key":"light","label":{"align":"center","direction":"x","label":"","level":"p","maxInlineSize":150,"orientation":"top"},"orientation":"left","scale":0.75,"source":{"props":{"connections":[{"from":"valueStream","to":"threshold"}],"outlet":"threshold","segments":{"threshold":{"props":{"trueBound":{"lower":0.9,"upper":1.1}},"type":"boolean-source","valueType":"boolean","variant":"source"},"valueStream":{"props":{"channel":1048777},"type":"stream-channel-value","valueType":"number","variant":"source"}}},"type":"source-pipeline","valueType":"boolean","variant":"source"}},"eCvVBWDpc3u":{"backgroundColor":[8,8,8,0],"borderRadius":3,"color":[43,32,243,1],"dimensions":{"height":150,"width":125},"key":"box","label":{"align":"center","direction":"x","label":"","level":"p","maxInlineSize":150,"orientation":"top"},"orientation":"left","scale":1,"strokeWidth":2},"eONVIHu4dtl":{"color":[250,250,250,1],"inlineSize":70,"key":"value","label":{"align":"center","direction":"x","label":"","level":"h2","maxInlineSize":150,"orientation":"top"},"level":"h2","orientation":"left","redline":{"bounds":{"lower":0,"upper":1},"gradient":[]},"scale":1,"stalenessColor":[0,0,0,0],"stalenessTimeout":5,"telem":{"props":{"connections":[{"from":"valueStream","to":"rollingAverage"},{"from":"rollingAverage","to":"stringifier"}],"outlet":"stringifier","segments":{"rollingAverage":{"props":{"windowSize":1},"type":"rolling-average","valueType":"number","variant":"source"},"stringifier":{"props":{"notation":"standard","precision":0,"prefix":"","suffix":""},"type":"stringify-number","valueType":"string","variant":"source"},"valueStream":{"props":{"channel":1048778},"type":"stream-channel-value","valueType":"number","variant":"source"}}},"type":"source-pipeline","valueType":"string","variant":"source"},"tooltip":["T_CLOCK_MIN"],"units":""},"eYZOED2MOJb":{"color":[240,219,151,1],"control":{"chip":{"sink":{"props":{"authority":255,"channel":1048752},"type":"acquire-channel-control","valueType":"boolean","variant":"sink"},"source":{"props":{"channel":1048752},"type":"controlled-status-source","valueType":"status","variant":"source"}},"indicator":{"statusSource":{"props":{"channel":1048752},"type":"controlled-status-source","valueType":"status","variant":"source"}},"show":true,"showChip":true,"showIndicator":true},"key":"button","label":{"align":"center","direction":"x","label":"Clear Main Hold","level":"h4","maxInlineSize":150,"orientation":"top"},"mode":"fire","onClickDelay":0,"orientation":"left","scale":null,"sink":{"props":{"connections":[{"from":"setpoint","to":"setter"}],"inlet":"setpoint","segments":{"setpoint":{"props":{"falsy":0,"truthy":1},"type":"boolean-numeric-converter-sink","valueType":"boolean","variant":"sink"},"setter":{"props":{"channel":1048752},"type":"controlled-numeric-telem-sink","valueType":"number","variant":"sink"}}},"type":"sink-pipeline","valueType":"boolean","variant":"sink"}},"gUDJiIx80cv":{"color":[52,198,26,1],"key":"light","label":{"align":"center","direction":"x","label":"","level":"p","maxInlineSize":150,"orientation":"top"},"orientation":"left","scale":0.75,"source":{"props":{"connections":[{"from":"valueStream","to":"threshold"}],"outlet":"threshold","segments":{"threshold":{"props":{"trueBound":{"lower":0.9,"upper":1.1}},"type":"boolean-source","valueType":"boolean","variant":"source"},"valueStream":{"props":{"channel":1048788},"type":"stream-channel-value","valueType":"number","variant":"source"}}},"type":"source-pipeline","valueType":"boolean","variant":"source"}},"guAvxEqaYEN":{"color":[55,116,208,1],"control":{"chip":{"sink":{"props":{"authority":255,"channel":1048782},"type":"acquire-channel-control","valueType":"boolean","variant":"sink"},"source":{"props":{"channel":1048782},"type":"controlled-status-source","valueType":"status","variant":"source"}},"indicator":{"statusSource":{"props":{"channel":1048782},"type":"controlled-status-source","valueType":"status","variant":"source"}},"show":true,"showChip":true,"showIndicator":true},"key":"button","label":{"align":"center","direction":"x","label":"Pull BB Setpoints","level":"p","maxInlineSize":150,"orientation":"top"},"mode":"fire","onClickDelay":0,"orientation":"left","scale":null,"sink":{"props":{"connections":[{"from":"setpoint","to":"setter"}],"inlet":"setpoint","segments":{"setpoint":{"props":{"falsy":0,"truthy":1},"type":"boolean-numeric-converter-sink","valueType":"boolean","variant":"sink"},"setter":{"props":{"channel":1048782},"type":"controlled-numeric-telem-sink","valueType":"number","variant":"sink"}}},"type":"sink-pipeline","valueType":"boolean","variant":"sink"}},"i1StPrP7t8X":{"color":[52,198,26,1],"key":"light","label":{"align":"center","direction":"x","label":"","level":"p","maxInlineSize":150,"orientation":"top"},"orientation":"left","scale":0.75,"source":{"props":{"connections":[{"from":"valueStream","to":"threshold"}],"outlet":"threshold","segments":{"threshold":{"props":{"trueBound":{"lower":0.9,"upper":1.1}},"type":"boolean-source","valueType":"boolean","variant":"source"},"valueStream":{"props":{"channel":1048773},"type":"stream-channel-value","valueType":"number","variant":"source"}}},"type":"source-pipeline","valueType":"boolean","variant":"source"}},"i1eKeB0jAmd":{"color":[237,237,10,1],"key":"light","label":{"align":"center","direction":"x","label":"Hold","level":"p","maxInlineSize":150,"orientation":"top"},"orientation":"left","scale":2,"source":{"props":{"connections":[{"from":"valueStream","to":"threshold"}],"outlet":"threshold","segments":{"threshold":{"props":{"trueBound":{"lower":0.9,"upper":1.1}},"type":"boolean-source","valueType":"boolean","variant":"source"},"valueStream":{"props":{"channel":1048767},"type":"stream-channel-value","valueType":"number","variant":"source"}}},"type":"source-pipeline","valueType":"boolean","variant":"source"}},"idpfxmP6pBd":{"color":[250,250,250,1],"key":"light","label":{"align":"center","direction":"x","label":"Light","level":"p","maxInlineSize":150,"orientation":"top"},"orientation":"left","scale":1,"source":{"props":{"connections":[{"from":"valueStream","to":"threshold"}],"outlet":"threshold","segments":{"threshold":{"props":{"trueBound":{"lower":0.9,"upper":1.1}},"type":"boolean-source","valueType":"boolean","variant":"source"},"valueStream":{"props":{"channel":0},"type":"stream-channel-value","valueType":"number","variant":"source"}}},"type":"source-pipeline","valueType":"boolean","variant":"source"}},"ilsYcVaUmcw":{"control":{"chip":{"sink":{"props":{"authority":255,"channel":1048680},"type":"acquire-channel-control","valueType":"boolean","variant":"sink"},"source":{"props":{"channel":1048680},"type":"controlled-status-source","valueType":"status","variant":"source"}},"indicator":{"statusSource":{"props":{"channel":1048680},"type":"controlled-status-source","valueType":"status","variant":"source"}},"show":true,"showChip":true,"showIndicator":true},"key":"switch","label":{"align":"center","direction":"x","label":"Shutdown Scripts","level":"p","maxInlineSize":150,"orientation":"top"},"orientation":"left","scale":null,"sink":{"props":{"connections":[{"from":"setpoint","to":"setter"}],"inlet":"setpoint","segments":{"setpoint":{"props":{"falsy":0,"truthy":1},"type":"boolean-numeric-converter-sink","valueType":"boolean","variant":"sink"},"setter":{"props":{"channel":1048680},"type":"controlled-numeric-telem-sink","valueType":"number","variant":"sink"}}},"type":"sink-pipeline","valueType":"boolean","variant":"sink"},"source":{"props":{"connections":[{"from":"valueStream","to":"threshold"}],"outlet":"threshold","segments":{"threshold":{"props":{"trueBound":{"lower":0.9,"upper":1.1}},"type":"boolean-source","valueType":"boolean","variant":"source"},"valueStream":{"props":{"channel":1048680},"type":"stream-channel-value","valueType":"number","variant":"source"}}},"type":"source-pipeline","valueType":"boolean","variant":"source"}},"j1XDAeK4elQ":{"backgroundColor":[8,8,8,0],"borderRadius":3,"color":[31,169,204,1],"dimensions":{"height":125,"width":200},"key":"box","label":{"align":"center","direction":"x","label":"","level":"p","maxInlineSize":150,"orientation":"top"},"orientation":"left","scale":1,"strokeWidth":2},"k8iTJxBeh5S":{"align":"center","autoFit":true,"color":[250,250,250,1],"dimensions":{"height":200,"width":125},"key":"textBox","label":{"align":"center","direction":"x","label":"Text Box","level":"p","maxInlineSize":150,"orientation":"top"},"level":"h2","orientation":"left","scale":1,"value":"Abort Armed","width":75},"kp6pQJdDEmH":{"color":[250,250,250,1],"control":{"show":true},"key":"solenoidValve","label":{"align":"center","direction":"x","label":"Fill QDs","level":"p","maxInlineSize":150,"orientation":"top"},"normallyOpen":false,"orientation":"left","scale":1,"sink":{"props":{"connections":[{"from":"setpoint","to":"setter"}],"inlet":"setpoint","segments":{"setpoint":{"props":{"falsy":0,"truthy":1},"type":"boolean-numeric-converter-sink","valueType":"boolean","variant":"sink"},"setter":{"props":{"channel":0},"type":"controlled-numeric-telem-sink","valueType":"number","variant":"sink"}}},"type":"sink-pipeline","valueType":"boolean","variant":"sink"},"source":{"props":{"connections":[{"from":"valueStream","to":"threshold"}],"outlet":"threshold","segments":{"threshold":{"props":{"trueBound":{"lower":0.9,"upper":1.1}},"type":"boolean-source","valueType":"boolean","variant":"source"},"valueStream":{"props":{"channel":0},"type":"stream-channel-value","valueType":"number","variant":"source"}}},"type":"source-pipeline","valueType":"boolean","variant":"source"}},"lwnjQauY6NM":{"backgroundColor":[8,8,8,0],"borderRadius":3,"color":[243,32,36,1],"dimensions":{"height":125,"width":125},"key":"box","label":{"align":"center","direction":"x","label":"","level":"p","maxInlineSize":150,"orientation":"top"},"orientation":"left","scale":1,"strokeWidth":2},"ny3NnIxOMSu":{"backgroundColor":[8,8,8,0],"borderRadius":3,"color":[43,32,243,1],"dimensions":{"height":150,"width":125},"key":"box","label":{"align":"center","direction":"x","label":"","level":"p","maxInlineSize":150,"orientation":"top"},"orientation":"left","scale":1,"strokeWidth":2},"o7rqO8fQjCR":{"color":[250,250,250,1],"control":{"chip":{"sink":{"props":{"authority":255,"channel":1048674},"type":"acquire-channel-control","valueType":"boolean","variant":"sink"},"source":{"props":{"channel":1048674},"type":"controlled-status-source","valueType":"status","variant":"source"}},"indicator":{"statusSource":{"props":{"channel":1048674},"type":"controlled-status-source","valueType":"status","variant":"source"}},"showChip":true,"showIndicator":true},"disabled":false,"key":"setpoint","label":{"align":"center","direction":"x","label":"Test Data Name","level":"p","maxInlineSize":150,"orientation":"top"},"orientation":"left","scale":1,"sink":{"props":{"connections":[],"inlet":"setter","segments":{"setter":{"props":{"channel":1048674},"type":"controlled-numeric-telem-sink","valueType":"number","variant":"sink"}}},"type":"sink-pipeline","valueType":"number","variant":"sink"},"size":"small","source":{"props":{"connections":[],"outlet":"valueStream","segments":{"valueStream":{"props":{"channel":0},"type":"stream-channel-value","valueType":"number","variant":"source"}}},"type":"source-pipeline","valueType":"number","variant":"source"},"units":""},"oO96dKEO9Nc":{"backgroundColor":[8,8,8,0],"borderRadius":3,"color":[243,32,36,1],"dimensions":{"height":62.5,"width":250},"key":"box","label":{"align":"center","direction":"x","label":"","level":"p","maxInlineSize":150,"orientation":"top"},"orientation":"left","scale":1,"strokeWidth":2},"offMVmNOxnL":{"control":{"chip":{"sink":{"props":{"authority":255,"channel":1048779},"type":"acquire-channel-control","valueType":"boolean","variant":"sink"},"source":{"props":{"channel":1048779},"type":"controlled-status-source","valueType":"status","variant":"source"}},"indicator":{"statusSource":{"props":{"channel":1048779},"type":"controlled-status-source","valueType":"status","variant":"source"}},"show":true,"showChip":true,"showIndicator":true},"key":"switch","label":{"align":"center","direction":"x","label":"Prepress Manual Override","level":"p","maxInlineSize":150,"orientation":"top"},"orientation":"left","scale":null,"sink":{"props":{"connections":[{"from":"setpoint","to":"setter"}],"inlet":"setpoint","segments":{"setpoint":{"props":{"falsy":0,"truthy":1},"type":"boolean-numeric-converter-sink","valueType":"boolean","variant":"sink"},"setter":{"props":{"channel":1048779},"type":"controlled-numeric-telem-sink","valueType":"number","variant":"sink"}}},"type":"sink-pipeline","valueType":"boolean","variant":"sink"},"source":{"props":{"connections":[{"from":"valueStream","to":"threshold"}],"outlet":"threshold","segments":{"threshold":{"props":{"trueBound":{"lower":0.9,"upper":1.1}},"type":"boolean-source","valueType":"boolean","variant":"source"},"valueStream":{"props":{"channel":1048779},"type":"stream-channel-value","valueType":"number","variant":"source"}}},"type":"source-pipeline","valueType":"boolean","variant":"source"}},"ouWyZNj7OtE":{"color":[250,250,250,1],"control":{"chip":{"sink":{"props":{"authority":255,"channel":1048762},"type":"acquire-channel-control","valueType":"boolean","variant":"sink"},"source":{"props":{"channel":1048762},"type":"controlled-status-source","valueType":"status","variant":"source"}},"indicator":{"statusSource":{"props":{"channel":1048762},"type":"controlled-status-source","valueType":"status","variant":"source"}},"showChip":true,"showIndicator":true},"disabled":false,"key":"setpoint","label":{"align":"center","direction":"x","label":"Clock Setpoint","level":"p","maxInlineSize":150,"orientation":"top"},"orientation":"left","scale":1,"sink":{"props":{"connections":[],"inlet":"setter","segments":{"setter":{"props":{"channel":1048762},"type":"controlled-numeric-telem-sink","valueType":"number","variant":"sink"}}},"type":"sink-pipeline","valueType":"number","variant":"sink"},"size":"small","source":{"props":{"connections":[],"outlet":"valueStream","segments":{"valueStream":{"props":{"channel":0},"type":"stream-channel-value","valueType":"number","variant":"source"}}},"type":"source-pipeline","valueType":"number","variant":"source"},"units":"m"},"p2YkFJIVuat":{"color":[250,250,250,1],"control":{"chip":{"sink":{"props":{"authority":255,"channel":1048639},"type":"acquire-channel-control","valueType":"boolean","variant":"sink"},"source":{"props":{"channel":1048639},"type":"controlled-status-source","valueType":"status","variant":"source"}},"indicator":{"statusSource":{"props":{"channel":1048639},"type":"controlled-status-source","valueType":"status","variant":"source"}},"show":true,"showChip":true,"showIndicator":true},"key":"solenoidValve","label":{"align":"center","direction":"x","label":"Purge","level":"p","maxInlineSize":150,"orientation":"top"},"normallyOpen":true,"orientation":"left","scale":1,"sink":{"props":{"connections":[{"from":"setpoint","to":"setter"}],"inlet":"setpoint","segments":{"setpoint":{"props":{"falsy":0,"truthy":1},"type":"boolean-numeric-converter-sink","valueType":"boolean","variant":"sink"},"setter":{"props":{"channel":1048639},"type":"controlled-numeric-telem-sink","valueType":"number","variant":"sink"}}},"type":"sink-pipeline","valueType":"boolean","variant":"sink"},"source":{"props":{"connections":[{"from":"valueStream","to":"threshold"}],"outlet":"threshold","segments":{"threshold":{"props":{"trueBound":{"lower":0.9,"upper":1.1}},"type":"boolean-source","valueType":"boolean","variant":"source"},"valueStream":{"props":{"channel":1048640},"type":"stream-channel-value","valueType":"number","variant":"source"}}},"type":"source-pipeline","valueType":"boolean","variant":"source"}},"pZvKJw4Hg8E":{"color":[52,198,26,1],"key":"light","label":{"align":"center","direction":"x","label":"","level":"p","maxInlineSize":150,"orientation":"top"},"orientation":"left","scale":0.75,"source":{"props":{"connections":[{"from":"valueStream","to":"threshold"}],"outlet":"threshold","segments":{"threshold":{"props":{"trueBound":{"lower":0.9,"upper":1.1}},"type":"boolean-source","valueType":"boolean","variant":"source"},"valueStream":{"props":{"channel":0},"type":"stream-channel-value","valueType":"number","variant":"source"}}},"type":"source-pipeline","valueType":"boolean","variant":"source"}},"pk0UfBkfphz":{"color":[250,250,250,1],"inlineSize":70,"key":"value","label":{"align":"center","direction":"x","label":"Value","level":"p","maxInlineSize":150,"orientation":"top"},"level":"h5","orientation":"left","redline":{"bounds":{"lower":0,"upper":1},"gradient":[]},"scale":1,"stalenessColor":[0,0,0,0],"stalenessTimeout":5,"telem":{"props":{"connections":[{"from":"valueStream","to":"rollingAverage"},{"from":"rollingAverage","to":"stringifier"}],"outlet":"stringifier","segments":{"rollingAverage":{"props":{"windowSize":1},"type":"rolling-average","valueType":"number","variant":"source"},"stringifier":{"props":{"notation":"standard","precision":2},"type":"stringify-number","valueType":"string","variant":"source"},"valueStream":{"props":{"channel":0},"type":"stream-channel-value","valueType":"number","variant":"source"}}},"type":"source-pipeline","valueType":"string","variant":"source"},"units":"psi"},"pl7lH9qH74s":{"color":[250,250,250,1],"key":"light","label":{"align":"center","direction":"x","label":"","level":"p","maxInlineSize":150,"orientation":"top"},"orientation":"left","scale":0.5,"source":{"props":{"connections":[{"from":"valueStream","to":"threshold"}],"outlet":"threshold","segments":{"threshold":{"props":{"trueBound":{"lower":0.9,"upper":1.1}},"type":"boolean-source","valueType":"boolean","variant":"source"},"valueStream":{"props":{"channel":1048798},"type":"stream-channel-value","valueType":"number","variant":"source"}}},"type":"source-pipeline","valueType":"boolean","variant":"source"}},"pzdDofmz4Dh":{"backgroundColor":[8,8,8,0],"borderRadius":3,"color":[243,32,36,1],"dimensions":{"height":62.5,"width":250},"key":"box","label":{"align":"center","direction":"x","label":"","level":"p","maxInlineSize":150,"orientation":"top"},"orientation":"left","scale":1,"strokeWidth":2},"qFxdJPzUv1Z":{"align":"center","autoFit":true,"color":[250,250,250,1],"dimensions":{"height":200,"width":125},"key":"textBox","label":{"align":"center","direction":"x","label":"Text Box","level":"p","maxInlineSize":150,"orientation":"top"},"level":"h2","orientation":"left","scale":1,"value":"Auto Armed","width":75},"qIzZwJadPfi":{"backgroundColor":[8,8,8,0],"borderRadius":3,"color":[31,169,204,1],"dimensions":{"height":200,"width":150},"key":"box","label":{"align":"center","direction":"x","label":"","level":"p","maxInlineSize":150,"orientation":"top"},"orientation":"left","scale":1,"strokeWidth":2},"sXQOz8Bwzk7":{"color":[250,250,250,1],"inlineSize":70,"key":"value","label":{"align":"center","direction":"x","label":"","level":"h2","maxInlineSize":150,"orientation":"top"},"level":"h2","orientation":"left","redline":{"bounds":{"lower":0,"upper":1},"gradient":[]},"scale":1,"stalenessColor":[0,0,0,0],"stalenessTimeout":5,"telem":{"props":{"connections":[{"from":"valueStream","to":"rollingAverage"},{"from":"rollingAverage","to":"stringifier"}],"outlet":"stringifier","segments":{"rollingAverage":{"props":{"windowSize":1},"type":"rolling-average","valueType":"number","variant":"source"},"stringifier":{"props":{"notation":"standard","precision":0,"prefix":"","suffix":""},"type":"stringify-number","valueType":"string","variant":"source"},"valueStream":{"props":{"channel":1048777},"type":"stream-channel-value","valueType":"number","variant":"source"}}},"type":"source-pipeline","valueType":"string","variant":"source"},"tooltip":["T_CLOCK_SEC"],"units":""},"sYXbvwRtkKV":{"align":"center","autoFit":true,"color":[250,250,250,1],"dimensions":{"height":200,"width":125},"key":"textBox","label":{"align":"center","direction":"x","label":"Text Box","level":"p","maxInlineSize":150,"orientation":"top"},"level":"h2","orientation":"left","scale":1,"value":"Auto Status","width":75},"tDsXbBZfvKg":{"backgroundColor":[8,8,8,0],"borderRadius":3,"color":[243,32,36,1],"dimensions":{"height":125,"width":125},"key":"box","label":{"align":"center","direction":"x","label":"","level":"p","maxInlineSize":150,"orientation":"top"},"orientation":"left","scale":1,"strokeWidth":2},"tMrMu0Pmjfn":{"backgroundColor":[8,8,8,0],"borderRadius":3,"color":[243,32,36,1],"dimensions":{"height":125,"width":125},"key":"box","label":{"align":"center","direction":"x","label":"","level":"p","maxInlineSize":150,"orientation":"top"},"orientation":"left","scale":1,"strokeWidth":2},"ut7UiwKeSrv":{"align":"center","autoFit":true,"color":[250,250,250,1],"dimensions":{"height":200,"width":125},"key":"textBox","label":{"align":"center","direction":"x","label":"Text Box","level":"p","maxInlineSize":150,"orientation":"top"},"level":"h2","orientation":"left","scale":1,"value":"Abort Active","width":75},"v6oBRzFONl5":{"color":[250,250,250,1],"control":{"chip":{"sink":{"props":{"authority":255,"channel":1048653},"type":"acquire-channel-control","valueType":"boolean","variant":"sink"},"source":{"props":{"channel":1048653},"type":"controlled-status-source","valueType":"status","variant":"source"}},"indicator":{"statusSource":{"props":{"channel":1048653},"type":"controlled-status-source","valueType":"status","variant":"source"}},"show":true,"showChip":true,"showIndicator":true},"key":"solenoidValve","label":{"align":"center","direction":"x","label":"Actuator","level":"p","maxInlineSize":150,"orientation":"top"},"normallyOpen":true,"orientation":"left","scale":1,"sink":{"props":{"connections":[{"from":"setpoint","to":"setter"}],"inlet":"setpoint","segments":{"setpoint":{"props":{"falsy":0,"truthy":1},"type":"boolean-numeric-converter-sink","valueType":"boolean","variant":"sink"},"setter":{"props":{"channel":1048653},"type":"controlled-numeric-telem-sink","valueType":"number","variant":"sink"}}},"type":"sink-pipeline","valueType":"boolean","variant":"sink"},"source":{"props":{"connections":[{"from":"valueStream","to":"threshold"}],"outlet":"threshold","segments":{"threshold":{"props":{"trueBound":{"lower":0.9,"upper":1.1}},"type":"boolean-source","valueType":"boolean","variant":"source"},"valueStream":{"props":{"channel":1048654},"type":"stream-channel-value","valueType":"number","variant":"source"}}},"type":"source-pipeline","valueType":"boolean","variant":"source"}},"vawv6tJ3Em2":{"backgroundColor":[8,8,8,0],"borderRadius":3,"color":[193,32,243,1],"dimensions":{"height":150,"width":125},"key":"box","label":{"align":"center","direction":"x","label":"","level":"p","maxInlineSize":150,"orientation":"top"},"orientation":"left","scale":1,"strokeWidth":2},"wr5ncX87Dsx":{"backgroundColor":[8,8,8,0],"borderRadius":3,"color":[243,32,36,1],"dimensions":{"height":125,"width":125},"key":"box","label":{"align":"center","direction":"x","label":"","level":"p","maxInlineSize":150,"orientation":"top"},"orientation":"left","scale":1,"strokeWidth":2},"xUZsu4b1fNZ":{"color":[250,250,250,1],"key":"light","label":{"align":"center","direction":"x","label":"Light","level":"p","maxInlineSize":150,"orientation":"top"},"orientation":"left","scale":1,"source":{"props":{"connections":[{"from":"valueStream","to":"threshold"}],"outlet":"threshold","segments":{"threshold":{"props":{"trueBound":{"lower":0.9,"upper":1.1}},"type":"boolean-source","valueType":"boolean","variant":"source"},"valueStream":{"props":{"channel":0},"type":"stream-channel-value","valueType":"number","variant":"source"}}},"type":"source-pipeline","valueType":"boolean","variant":"source"}},"xXYJd3DUmQR":{"color":[250,250,250,1],"control":{"chip":{"sink":{"props":{"authority":255,"channel":1048645},"type":"acquire-channel-control","valueType":"boolean","variant":"sink"},"source":{"props":{"channel":1048645},"type":"controlled-status-source","valueType":"status","variant":"source"}},"indicator":{"statusSource":{"props":{"channel":1048645},"type":"controlled-status-source","valueType":"status","variant":"source"}},"show":true,"showChip":true,"showIndicator":true},"key":"solenoidValve","label":{"align":"center","direction":"x","label":"Helium QD","level":"p","maxInlineSize":150,"orientation":"top"},"normallyOpen":true,"orientation":"left","scale":1,"sink":{"props":{"connections":[{"from":"setpoint","to":"setter"}],"inlet":"setpoint","segments":{"setpoint":{"props":{"falsy":0,"truthy":1},"type":"boolean-numeric-converter-sink","valueType":"boolean","variant":"sink"},"setter":{"props":{"channel":1048645},"type":"controlled-numeric-telem-sink","valueType":"number","variant":"sink"}}},"type":"sink-pipeline","valueType":"boolean","variant":"sink"},"source":{"props":{"connections":[{"from":"valueStream","to":"threshold"}],"outlet":"threshold","segments":{"threshold":{"props":{"trueBound":{"lower":0.9,"upper":1.1}},"type":"boolean-source","valueType":"boolean","variant":"source"},"valueStream":{"props":{"channel":1048646},"type":"stream-channel-value","valueType":"number","variant":"source"}}},"type":"source-pipeline","valueType":"boolean","variant":"source"}},"xjD5iZCxHZX":{"align":"center","autoFit":true,"color":[250,250,250,1],"dimensions":{"height":200,"width":125},"key":"textBox","label":{"align":"center","direction":"x","label":"Text Box","level":"p","maxInlineSize":150,"orientation":"top"},"level":"h2","orientation":"left","scale":1,"value":"Abort Active","width":75},"yE8Tbra1jL8":{"control":{"chip":{"sink":{"props":{"authority":255,"channel":1048764},"type":"acquire-channel-control","valueType":"boolean","variant":"sink"},"source":{"props":{"channel":1048764},"type":"controlled-status-source","valueType":"status","variant":"source"}},"indicator":{"statusSource":{"props":{"channel":1048764},"type":"controlled-status-source","valueType":"status","variant":"source"}},"show":true,"showChip":true,"showIndicator":true},"key":"switch","label":{"align":"center","direction":"x","label":"Clock Switch","level":"p","maxInlineSize":150,"orientation":"top"},"orientation":"left","scale":null,"sink":{"props":{"connections":[{"from":"setpoint","to":"setter"}],"inlet":"setpoint","segments":{"setpoint":{"props":{"falsy":0,"truthy":1},"type":"boolean-numeric-converter-sink","valueType":"boolean","variant":"sink"},"setter":{"props":{"channel":1048764},"type":"controlled-numeric-telem-sink","valueType":"number","variant":"sink"}}},"type":"sink-pipeline","valueType":"boolean","variant":"sink"},"source":{"props":{"connections":[{"from":"valueStream","to":"threshold"}],"outlet":"threshold","segments":{"threshold":{"props":{"trueBound":{"lower":0.9,"upper":1.1}},"type":"boolean-source","valueType":"boolean","variant":"source"},"valueStream":{"props":{"channel":1048766},"type":"stream-channel-value","valueType":"number","variant":"source"}}},"type":"source-pipeline","valueType":"boolean","variant":"source"}},"ysXQFPUAtNh":{"control":{"chip":{"sink":{"props":{"authority":255,"channel":1048780},"type":"acquire-channel-control","valueType":"boolean","variant":"sink"},"source":{"props":{"channel":1048780},"type":"controlled-status-source","valueType":"status","variant":"source"}},"indicator":{"statusSource":{"props":{"channel":1048780},"type":"controlled-status-source","valueType":"status","variant":"source"}},"show":true,"showChip":true,"showIndicator":true},"key":"switch","label":{"align":"center","direction":"x","label":"Clear Main Hold","level":"p","maxInlineSize":150,"orientation":"top"},"orientation":"left","scale":null,"sink":{"props":{"connections":[{"from":"setpoint","to":"setter"}],"inlet":"setpoint","segments":{"setpoint":{"props":{"falsy":0,"truthy":1},"type":"boolean-numeric-converter-sink","valueType":"boolean","variant":"sink"},"setter":{"props":{"channel":1048780},"type":"controlled-numeric-telem-sink","valueType":"number","variant":"sink"}}},"type":"sink-pipeline","valueType":"boolean","variant":"sink"},"source":{"props":{"connections":[{"from":"valueStream","to":"threshold"}],"outlet":"threshold","segments":{"threshold":{"props":{"trueBound":{"lower":0.9,"upper":1.1}},"type":"boolean-source","valueType":"boolean","variant":"source"},"valueStream":{"props":{"channel":1048781},"type":"stream-channel-value","valueType":"number","variant":"source"}}},"type":"source-pipeline","valueType":"boolean","variant":"source"}},"yujFCP6rMFg":{"control":{"chip":{"sink":{"props":{"authority":255,"channel":1048776},"type":"acquire-channel-control","valueType":"boolean","variant":"sink"},"source":{"props":{"channel":1048776},"type":"controlled-status-source","valueType":"status","variant":"source"}},"indicator":{"statusSource":{"props":{"channel":1048776},"type":"controlled-status-source","valueType":"status","variant":"source"}},"show":true,"showChip":true,"showIndicator":true},"key":"switch","label":{"align":"center","direction":"x","label":"Arm Auto","level":"p","maxInlineSize":150,"orientation":"top"},"orientation":"left","scale":null,"sink":{"props":{"connections":[{"from":"setpoint","to":"setter"}],"inlet":"setpoint","segments":{"setpoint":{"props":{"falsy":0,"truthy":1},"type":"boolean-numeric-converter-sink","valueType":"boolean","variant":"sink"},"setter":{"props":{"channel":1048776},"type":"controlled-numeric-telem-sink","valueType":"number","variant":"sink"}}},"type":"sink-pipeline","valueType":"boolean","variant":"sink"},"source":{"props":{"connections":[{"from":"valueStream","to":"threshold"}],"outlet":"threshold","segments":{"threshold":{"props":{"trueBound":{"lower":0.9,"upper":1.1}},"type":"boolean-source","valueType":"boolean","variant":"source"},"valueStream":{"props":{"channel":1048778},"type":"stream-channel-value","valueType":"number","variant":"source"}}},"type":"source-pipeline","valueType":"boolean","variant":"source"}},"z85yKDcru40":{"backgroundColor":[52,198,26,1],"borderRadius":3,"color":[243,32,36,1],"dimensions":{"height":125,"width":125},"key":"box","label":{"align":"center","direction":"x","label":"","level":"p","maxInlineSize":150,"orientation":"top"},"orientation":"left","scale":1,"strokeWidth":2},"zYOnWxyynSd":{"backgroundColor":[8,8,8,0],"borderRadius":3,"color":[43,32,243,1],"dimensions":{"height":150,"width":125},"key":"box","label":{"align":"center","direction":"x","label":"","level":"p","maxInlineSize":150,"orientation":"top"},"orientation":"left","scale":1,"strokeWidth":2},"zz1YKrolF6v":{"color":[52,198,26,1],"key":"light","label":{"align":"center","direction":"x","label":"","level":"p","maxInlineSize":150,"orientation":"top"},"orientation":"left","scale":0.75,"source":{"props":{"connections":[{"from":"valueStream","to":"threshold"}],"outlet":"threshold","segments":{"threshold":{"props":{"trueBound":{"lower":0.9,"upper":1.1}},"type":"boolean-source","valueType":"boolean","variant":"source"},"valueStream":{"props":{"channel":1048774},"type":"stream-channel-value","valueType":"number","variant":"source"}}},"type":"source-pipeline","valueType":"boolean","variant":"source"}}},"remoteCreated":true,"snapshot":false,"toolbar":{"activeTab":"symbols","selectedSymbolGroup":"valves"},"type":"schematic","version":"5.0.0","viewport":{"position":{"x":-461.4336216354046,"y":276.7557169001943},"zoom":1},"viewportMode":"select"}